simrank_cmp/__init__.py
simrank_cmp/sims.py
simrank_cmp-1.0.3.dist-info/LICENSE
simrank_cmp-1.0.3.dist-info/METADATA
simrank_cmp-1.0.3.dist-info/WHEEL
simrank_cmp-1.0.3.dist-info/top_level.txt
simrank_cmp-1.0.3.dist-info/RECORD
