Metadata-Version: 2.1
Name: simrank-cmp
Version: 1.0.3
Summary: Exact SimRank similarities for small graphs
Author-email: rzqx <rzqx@pm.me>
License: MIT License        
Project-URL: Homepage, https://github.com/rzqx/simrank_cmp
Project-URL: Bug Tracker, https://github.com/rzqx/simrank_cmp/issues
Classifier: Programming Language :: Python :: 3
Classifier: License :: OSI Approved :: MIT License
Classifier: Operating System :: OS Independent
Requires-Python: >=3.7
License-File: LICENSE
